spacy_lefff/__init__.py
spacy_lefff/__main__.py
spacy_lefff/data/LICENSE
spacy_lefff/data/lefff-3.4.mlex
spacy_lefff/data/lefff-tagset-0.1.2.pdf
spacy_lefff/downloader.py
spacy_lefff/lefff.py
spacy_lefff/mappings.py
spacy_lefff/melt_tagger.py
spacy_lefff-0.5.1.dist-info/LICENSE
spacy_lefff-0.5.1.dist-info/WHEEL
spacy_lefff-0.5.1.dist-info/METADATA
spacy_lefff-0.5.1.dist-info/RECORD
