Metadata-Version: 2.1
Name: spacy-lefff
Version: 0.5.1
Summary: Custom French POS and lemmatizer based on Lefff for spacy
Home-page: https://github.com/sammous/spacy-lefff
License: MIT
Author: Sami Moustachir
Requires-Python: >=3.8
Classifier: Development Status :: 3 - Alpha
Classifier: Environment :: Console
Classifier: Intended Audience :: Developers
Classifier: Intended Audience :: Science/Research
Classifier: License :: OSI Approved :: MIT License
Classifier: Natural Language :: English
Classifier: Operating System :: OS Independent
Classifier: Programming Language :: Python
Classifier: Programming Language :: Python :: 3
Classifier: Programming Language :: Python :: 3.10
Classifier: Programming Language :: Python :: 3.8
Classifier: Programming Language :: Python :: 3.9
Classifier: Topic :: Scientific/Engineering
Classifier: Topic :: Software Development :: Libraries :: Python Modules
Requires-Dist: black (>=22.6.0,<23.0.0)
Requires-Dist: msgpack (>=0.3.0,<0.6)
Requires-Dist: pluggy (>=0.12.0)
Requires-Dist: spacy
Requires-Dist: tqdm (>=4.11.1)
Project-URL: Repository, https://github.com/sammous/spacy-lefff
